ipsuite_core/__init__.py
ipsuite_core/base/__init__.py
ipsuite_core/base/base.py
ipsuite_core/base/selection.py
ipsuite_core/fields/__init__.py
ipsuite_core/fields/atoms.py
ipsuite_core/protocol/__init__.py
ipsuite_core/protocol/protocols.py
ipsuite_core-0.1.0.dist-info/LICENSE
ipsuite_core-0.1.0.dist-info/METADATA
ipsuite_core-0.1.0.dist-info/WHEEL
ipsuite_core-0.1.0.dist-info/RECORD
